tree_config/__init__.py
tree_config/doc_gen.py
tree_config/utils.py
tree_config/yaml.py
tree_config/tests/__init__.py
tree_config/tests/doc_dummy_class.py
tree_config/tests/test_config.py
tree_config/tests/test_config_file.py
tree_config/tests/test_doc.py
tree_config-1.0.2.dist-info/LICENSE
tree_config-1.0.2.dist-info/METADATA
tree_config-1.0.2.dist-info/WHEEL
tree_config-1.0.2.dist-info/top_level.txt
tree_config-1.0.2.dist-info/RECORD
