Metadata-Version: 2.1
Name: tree-config
Version: 1.0.2
Summary: Automatic app configuration of app objects.
Home-page: https://github.com/matham/tree-config
Author: Matthew Einhorn
Author-email: matt@einhorn.dev
License: MIT
Project-URL: Bug Reports, https://github.com/matham/tree-config/issues
Project-URL: Source, https://github.com/matham/tree-config
Platform: UNKNOWN
Classifier: Development Status :: 4 - Beta
Classifier: License :: OSI Approved :: MIT License
Classifier: Programming Language :: Python :: 3.7
Classifier: Programming Language :: Python :: 3.8
Classifier: Programming Language :: Python :: 3.9
Classifier: Programming Language :: Python :: 3.10
License-File: LICENSE
Requires-Dist: ruamel.yaml
Provides-Extra: dev
Requires-Dist: pytest (>=3.6) ; extra == 'dev'
Requires-Dist: pytest-cov ; extra == 'dev'
Requires-Dist: sphinx-rtd-theme ; extra == 'dev'
Requires-Dist: coveralls ; extra == 'dev'
Requires-Dist: sphinx ; extra == 'dev'
Requires-Dist: flake8 ; extra == 'dev'
Requires-Dist: wheel ; extra == 'dev'
